tg_gateway/__init__.py
tg_gateway/__meta__.py
tg_gateway/client.py
tg_gateway/const.py
tg_gateway/exceptions.py
tg_gateway/py.typed
tg_gateway/enums/__init__.py
tg_gateway/enums/delivery_status_type.py
tg_gateway/enums/verification_status_type.py
tg_gateway/methods/__init__.py
tg_gateway/methods/base.py
tg_gateway/methods/check_send_ability.py
tg_gateway/methods/check_verification_status.py
tg_gateway/methods/revoke_verification_message.py
tg_gateway/methods/send_verification_message.py
tg_gateway/types/__init__.py
tg_gateway/types/base.py
tg_gateway/types/custom.py
tg_gateway/types/delivery_status.py
tg_gateway/types/request_status.py
tg_gateway/types/verification_status.py
tg_gateway-1.0.dist-info/METADATA
tg_gateway-1.0.dist-info/WHEEL
tg_gateway-1.0.dist-info/licenses/LICENSE
tg_gateway-1.0.dist-info/RECORD
